dmitallx/__init__.py
dmitallx/utils.py
dmitallx-0.1.2.dist-info/METADATA
dmitallx-0.1.2.dist-info/WHEEL
dmitallx-0.1.2.dist-info/top_level.txt
dmitallx-0.1.2.dist-info/RECORD
