Metadata-Version: 2.2
Name: dmitallx
Version: 0.1.2
Summary: Небольшая библиотека для упрощения привычных действий.
Home-page: https://github.com/Hieso/dmitallx
Author: DmitX
Author-email: Hieso123@yandex.com
Classifier: Programming Language :: Python :: 3
Classifier: License :: OSI Approved :: MIT License
Classifier: Operating System :: OS Independent
Requires-Python: >=3.6
Requires-Dist: rich
Requires-Dist: operator
Dynamic: author
Dynamic: author-email
Dynamic: classifier
Dynamic: description
Dynamic: description-content-type
Dynamic: home-page
Dynamic: requires-dist
Dynamic: requires-python
Dynamic: summary
